MANIFEST.in
README.rst
setup.cfg
setup.py
evidence/__init__.py
evidence/__main__.py
evidence/tests/__init__.py
evidence/tests/test.py
evidence/tests/assets/__init__.py
evidence/theory/__init__.py
evidence/theory/dst.py
evidence/utils/__init__.py
evidence/utils/ext.py
evidence/utils/lib.py
evidencetheory.egg-info/PKG-INFO
evidencetheory.egg-info/SOURCES.txt
evidencetheory.egg-info/dependency_links.txt
evidencetheory.egg-info/top_level.txt
evidencetheory.egg-info/zip-safe