Metadata-Version: 1.1
Name: evidencetheory
Version: 0.0.1
Summary: Evidence Theory
Home-page: https://github.com/d555/evidencetheory
Author: Jonathan S. Prieto
Author-email: prieto.jona@gmail.com
License: MIT
Download-URL: https://github.com/d555/evidencetheory/
Keywords: evidencetheory dempster shafer fusion information
Platform: UNKNOWN
Classifier: Intended Audience :: Information Technology
